breath_data/__init__.py
breath_data/bd_acess_point/__init__.py
breath_data/bd_acess_point/service.py
breath_data/bd_acess_point/graph_querier/__init__.py
breath_data/bd_acess_point/graph_querier/graph_querier.py
breath_data/bd_acess_point/relational_querier/__init__.py
breath_data/bd_acess_point/relational_querier/dados_climaticos.py
breath_data/bd_acess_point/relational_querier/dataSUS.py
breath_data/bd_acess_point/relational_querier/relational_querier.py
breath_data/data_workflow/__init__.py
breath_data/data_workflow/climate.py
breath_data/data_workflow/dados_climaticos.py
breath_data/data_workflow/data_download.py
breath_data/data_workflow/ibge.py
breath_data/data_workflow/open_sus.py
breath_data/data_workflow/service.py
breath_data/data_workflow/workflow.py
breath_data-0.2.0.dist-info/METADATA
breath_data-0.2.0.dist-info/WHEEL
breath_data-0.2.0.dist-info/top_level.txt
breath_data-0.2.0.dist-info/RECORD
